README.rst
setup.py
src/c10k/__init__.py
src/c10k/__main__.py
src/c10k.egg-info/PKG-INFO
src/c10k.egg-info/SOURCES.txt
src/c10k.egg-info/dependency_links.txt
src/c10k.egg-info/entry_points.txt
src/c10k.egg-info/top_level.txt